viqa-2.2.3.dist-info/WHEEL
viqa-2.2.3.dist-info/RECORD
viqa-2.2.3.dist-info/METADATA
viqa/_metrics.py
viqa/multiple.py
viqa/kernels.py
viqa/__init__.py
viqa/fusion.py
viqa/fr_metrics/rmse.py
viqa/fr_metrics/vif.py
viqa/fr_metrics/mad.py
viqa/fr_metrics/msssim.py
viqa/fr_metrics/psnr.py
viqa/fr_metrics/fsim.py
viqa/fr_metrics/uqi.py
viqa/fr_metrics/__init__.py
viqa/fr_metrics/ssim.py
viqa/fr_metrics/vsi.py
viqa/fr_metrics/gsm.py
viqa/fr_metrics/stat_utils/statisticscalc.pyi
viqa/fr_metrics/stat_utils/statisticscalc.cpython-312-x86_64-linux-gnu.so
viqa/nr_metrics/cnr.py
viqa/nr_metrics/qmeasure.py
viqa/nr_metrics/__init__.py
viqa/nr_metrics/snr.py
viqa/nr_metrics/qmeasure_utils/qmeasurecalc.pyi
viqa/nr_metrics/qmeasure_utils/qmeasurecalc.cpython-312-x86_64-linux-gnu.so
viqa/utils/visualization.py
viqa/utils/_module.py
viqa/utils/loading.py
viqa/utils/deprecation.py
viqa/utils/export.py
viqa/utils/__init__.py
viqa/utils/misc.py
