Metadata-Version: 2.1
Name: vIQA
Version: 2.2.3
Summary: A Python package for volumetric image quality assessment.
Keywords: IQA,image quality assessment,volumetric data,image comparison,CT,computed tomography
Author-Email: Lukas Behammer <lukas.behammer@fh-wels.at>
License: BSD-3-Clause
Classifier: Development Status :: 5 - Production/Stable
Classifier: Intended Audience :: Science/Research
Classifier: Natural Language :: English
Classifier: Topic :: Scientific/Engineering :: Image Processing
Classifier: License :: OSI Approved :: BSD License
Classifier: Programming Language :: Python :: 3 :: Only
Classifier: Programming Language :: Python :: 3.11
Classifier: Programming Language :: Python :: 3.12
Classifier: Programming Language :: Python :: 3.13
Classifier: Programming Language :: C
Classifier: Programming Language :: C++
Classifier: Operating System :: Microsoft :: Windows
Classifier: Operating System :: Unix
Project-URL: Repository, https://github.com/3dct/vIQA
Project-URL: Documentation, https://3dct.github.io/vIQA/
Project-URL: Tracker, https://github.com/3dct/vIQA/issues
Project-URL: Download, https://pypi.org/project/vIQA/#files
Requires-Python: >=3.11
Requires-Dist: scipy>=1.10.0
Requires-Dist: numpy<2.0.0,>=1.24.0
Requires-Dist: torch>=1.13.0
Requires-Dist: piq>=0.8.0
Requires-Dist: scikit-image>=0.19.0
Requires-Dist: nibabel>=5.0.0
Requires-Dist: matplotlib>=3.5.0
Requires-Dist: tqdm>=4.65.0
Provides-Extra: book
Requires-Dist: jupyter>=1.0.0; extra == "book"
Requires-Dist: ipywidgets>=8.1.2; extra == "book"
Provides-Extra: tests
Requires-Dist: pytest>=8.2.1; extra == "tests"
Requires-Dist: pytest-cov>=5.0.0; extra == "tests"
Requires-Dist: pytest-doctestplus>=1.2.1; extra == "tests"
Provides-Extra: lint
Requires-Dist: mypy==1.14.1; extra == "lint"
Requires-Dist: ruff==0.11.0; extra == "lint"
Provides-Extra: docs
Requires-Dist: sphinx>=7.3.7; extra == "docs"
Requires-Dist: furo>=2024.5.6; extra == "docs"
Requires-Dist: sphinxcontrib-email>=0.3.6; extra == "docs"
Requires-Dist: sphinx_copybutton>=0.5.2; extra == "docs"
Requires-Dist: sphinx_github_changelog>=1.4.0; extra == "docs"
Requires-Dist: sphinx-last-updated-by-git>=0.3.8; extra == "docs"
Requires-Dist: viqa[tests]; extra == "docs"
Provides-Extra: cd
Requires-Dist: python-semantic-release==9.21.0; extra == "cd"
Requires-Dist: cibuildwheel==2.19.2; extra == "cd"
Provides-Extra: build
Requires-Dist: meson-python>=0.16.0; extra == "build"
Requires-Dist: build>=1.2.1; extra == "build"
Provides-Extra: dev
Requires-Dist: viqa[build,cd,docs,lint,tests]; extra == "dev"
Requires-Dist: pre-commit>=3.8.0; extra == "dev"
Requires-Dist: sphinx-autobuild>=2024.4.16; extra == "dev"
